boredStats/__init__.py
boredStats/corr_tools.py
boredStats/pca_tools.py
boredStats/pls_tools.py
boredStats/utils.py
boredStats-0.3.1.dist-info/LICENSE
boredStats-0.3.1.dist-info/METADATA
boredStats-0.3.1.dist-info/WHEEL
boredStats-0.3.1.dist-info/top_level.txt
boredStats-0.3.1.dist-info/RECORD
