Metadata-Version: 2.1
Name: boredStats
Version: 0.3.1
Summary: Personal stats tools
Home-page: http://github.com/boredStats/boredStats
Author: Pixie
Author-email: ian.abenes@gmail.com
License: MIT
Platform: UNKNOWN
